AEH/AE.py
AEH/__init__.py
AEH/enc.py
AEH-0.1.0.dist-info/METADATA
AEH-0.1.0.dist-info/WHEEL
AEH-0.1.0.dist-info/top_level.txt
AEH-0.1.0.dist-info/RECORD
