Metadata-Version: 2.1
Name: AEH
Version: 0.1.0
Summary: A New Encryption Algorithim
Home-page: UNKNOWN
Author: Ali Al Hadi Al-Husseini
Author-email: <alihadi.alhusseini@gmail.com>
License: UNKNOWN
Keywords: python,encryption,decrypting
Platform: UNKNOWN
Classifier: Development Status :: 1 - Planning
Classifier: Intended Audience :: Developers
Classifier: Programming Language :: Python :: 3
Classifier: Operating System :: Unix
Classifier: Operating System :: MacOS :: MacOS X
Classifier: Operating System :: Microsoft :: Windows
